rmf/__init__.py
rmf/couplings.py
rmf/librmf.cpython-310-x86_64-linux-gnu.so
rmf/rmf_wrapper.py
rmf-0.1.1.dist-info/METADATA
rmf-0.1.1.dist-info/WHEEL
rmf-0.1.1.dist-info/top_level.txt
rmf-0.1.1.dist-info/RECORD
