Metadata-Version: 2.4
Name: rmf
Version: 0.1.1
Summary: Relativistic Mean Field package for neutron star and nuclear matter equation of state
Author: Zhenyu Zhu
Author-email: zxzsma@rit.edu
License: MIT
Classifier: Programming Language :: Python :: 3
Classifier: Operating System :: OS Independent
Classifier: License :: OSI Approved :: MIT License
Requires-Python: >=3.9
Requires-Dist: jax>=0.4.30
Dynamic: author
Dynamic: author-email
Dynamic: classifier
Dynamic: description
Dynamic: description-content-type
Dynamic: license
Dynamic: requires-dist
Dynamic: requires-python
Dynamic: summary
